rackcli/__init__.py
rackcli/__main__.py
rackcli/config.py
rackcli/rackcli.py
rackcli-0.1.1.dist-info/DESCRIPTION.rst
rackcli-0.1.1.dist-info/entry_points.txt
rackcli-0.1.1.dist-info/METADATA
rackcli-0.1.1.dist-info/metadata.json
rackcli-0.1.1.dist-info/pbr.json
rackcli-0.1.1.dist-info/RECORD
rackcli-0.1.1.dist-info/top_level.txt
rackcli-0.1.1.dist-info/WHEEL
