Metadata-Version: 2.0
Name: rackcli
Version: 0.1.1
Summary: minimalistic rackspace cloud cli based on python-openstacksdk
Home-page: https://github.com/jnoller/rackcli
Author: Jesse Noller
Author-email: jesse.noller@rackspace.com
License: BSD
Keywords: rackcli
Platform: UNKNOWN
Classifier: Development Status :: 2 - Pre-Alpha
Classifier: Intended Audience :: Developers
Classifier: License :: OSI Approved :: BSD License
Classifier: Natural Language :: English
Classifier: Programming Language :: Python :: 2
Classifier: Programming Language :: Python :: 2.6
Classifier: Programming Language :: Python :: 2.7
Classifier: Programming Language :: Python :: 3
Classifier: Programming Language :: Python :: 3.3
Classifier: Programming Language :: Python :: 3.4
